openverb/__init__.py
openverb/openverb.core.json
openverb-0.1.0.dist-info/METADATA
openverb-0.1.0.dist-info/WHEEL
openverb-0.1.0.dist-info/licenses/LICENSE
openverb-0.1.0.dist-info/RECORD
