Metadata-Version: 2.4
Name: openverb
Version: 0.1.0
Summary: Helpers for loading and validating OpenVerb verb libraries
Project-URL: Homepage, https://openverb.org
Project-URL: Repository, https://github.com/sgthancel/openverb
Project-URL: Issues, https://github.com/sgthancel/openverb/issues
Author-email: Roman Hancel <roman@romanhancel.com>
License: MIT
License-File: LICENSE
Keywords: actions,agent,ai,llm,openverb,verbs
Classifier: Development Status :: 4 - Beta
Classifier: Intended Audience :: Developers
Classifier: License :: OSI Approved :: MIT License
Classifier: Programming Language :: Python :: 3
Classifier: Programming Language :: Python :: 3.8
Classifier: Programming Language :: Python :: 3.9
Classifier: Programming Language :: Python :: 3.10
Classifier: Programming Language :: Python :: 3.11
Classifier: Programming Language :: Python :: 3.12
Requires-Python: >=3.8
